[
  {
    "id": "1777974769873",
    "name": "Raj Kumar",
    "email": "rajkmr98752@gmail.com",
    "phone": "7973524694",
    "city": "patna",
    "usertype": "student",
    "password": "$2b$10$pciikBNP3sfVHeOZehI8dOtGG51y4vs2kxWZdeyoFjDMOxqKgDhr6",
    "createdAt": "2026-05-05T09:52:49.873Z",
    "updatedAt": "2026-05-05T09:52:49.873Z",
    "otp": null,
    "otpExpiry": null
  },
  {
    "id": "1777978501224",
    "name": "Vivekkumar",
    "email": "vivektest@gmail.com",
    "phone": "9874563210",
    "city": "chapra",
    "usertype": "student",
    "password": "$2b$12$XwJceK0aggzO8XcLwlksk.pbND33jVA2YqMkrOVfBb4oL8gx69M86",
    "createdAt": "2026-05-05T10:55:01.224Z",
    "updatedAt": "2026-05-05T10:55:01.224Z"
  },
  {
    "id": "1778038428223",
    "name": "Test1",
    "email": "test1@gmail.com",
    "phone": "9874563210",
    "city": "chapra",
    "usertype": "student",
    "password": "$2b$12$ODOFZ.1rFxyXnqkQMu2XdejwOPaA8uextNk5lSDAPOrBE5Tu.tZjS",
    "createdAt": "2026-05-06T03:33:48.222Z",
    "updatedAt": "2026-05-06T03:33:48.222Z"
  },
  {
    "id": "1778052728574",
    "name": "guru kashi",
    "email": "gurukashi@gmail.com",
    "phone": "9874563210",
    "city": "bhatinda",
    "usertype": "student",
    "password": "$2b$12$RDQgeIrNfBbktb.m1GPv7OcreQLBKeSIz9oe5EIGyarRjtwVhx12K",
    "createdAt": "2026-05-06T07:32:08.574Z",
    "updatedAt": "2026-05-06T07:32:08.574Z"
  },
  {
    "id": "1778062118825",
    "name": "amit kumar",
    "email": "amit@gmail.com",
    "phone": "6240032580",
    "city": "chapra",
    "usertype": "student",
    "password": "$2b$12$O4IbdNFOcROJK7OZK4ALTuzowfFltrSMSnzSeZAS3gUK9cCALFWD.",
    "createdAt": "2026-05-06T10:08:38.825Z",
    "updatedAt": "2026-05-06T10:08:38.825Z"
  },
  {
    "id": "1778155793879",
    "name": "nitin kumar",
    "email": "nitin@gmail.com",
    "phone": "9874563210",
    "city": "facebook",
    "usertype": "student",
    "password": "$2b$12$869tPx5xmAEHjomj2Q5JpOQkn2YTRcGrAgZ1k1tVEMViNo5uTzQFm",
    "createdAt": "2026-05-07T12:09:53.879Z",
    "updatedAt": "2026-05-07T12:09:53.879Z"
  },
  {
    "id": "1778306018013",
    "name": "Test5",
    "email": "test5@gmail.com",
    "phone": "9874563210",
    "city": "chapra",
    "usertype": "student",
    "password": "$2b$12$e41wEDJluxSwA0DHFcVhtOsVq2ZEwJhJWXqWATWWPmAkKCcFt.6Fa",
    "createdAt": "2026-05-09T05:53:38.012Z",
    "updatedAt": "2026-05-09T05:53:38.012Z"
  },
  {
    "id": "1779705406958",
    "name": "gkutest",
    "email": "gkutest@gmail.com",
    "phone": "7412859630",
    "city": "bhatinda",
    "usertype": "admin",
    "password": "$2b$12$27vjHvvz9Je4dQzSSa6mf.eePom3BMic66XPNyQKprOZs6D3l9H6K",
    "createdAt": "2026-05-25T10:36:46.958Z",
    "updatedAt": "2026-05-25T10:36:46.958Z"
  }
]